LICENSE
MANIFEST.in
README.md
setup.py
async_mcrcon/__init__.py
async_mcrcon/__version__.py
async_mcrcon/async_mcrcon.py
async_mcrcon.egg-info/PKG-INFO
async_mcrcon.egg-info/SOURCES.txt
async_mcrcon.egg-info/dependency_links.txt
async_mcrcon.egg-info/top_level.txt