Metadata-Version: 2.1
Name: async-mcrcon
Version: 0.1.0
Summary: A MineCraft RCON package.
Home-page: https://jiushu.info
Author: Provias
Author-email: 1686886163@qq.com
License: MIT
Classifier: License :: OSI Approved :: MIT License
Classifier: Programming Language :: Python
Classifier: Programming Language :: Python :: 3
Classifier: Programming Language :: Python :: 3.6
Classifier: Programming Language :: Python :: Implementation :: CPython
Classifier: Programming Language :: Python :: Implementation :: PyPy
Requires-Python: >=3.6.0
License-File: LICENSE
